tfbox/__init__.py
tfbox/callbacks/__init__.py
tfbox/callbacks/tensorboard.py
tfbox/loaders/__init__.py
tfbox/loaders/dfsequence.py
tfbox/losses/__init__.py
tfbox/losses/utils.py
tfbox/losses/weighted.py
tfbox/metrics/__init__.py
tfbox/metrics/weighted.py
tfbox/nn/__init__.py
tfbox/nn/addons.py
tfbox/nn/base.py
tfbox/nn/blocks.py
tfbox/nn/decoder.py
tfbox/nn/encoder.py
tfbox/nn/encoder_decoder.py
tfbox/nn/load.py
tfbox/nn/configs/blocks.yaml
tfbox/nn/configs/decoder.yaml
tfbox/nn/configs/encoder.yaml
tfbox/nn/configs/encoder_decoder.yaml
tfbox/utils/__init__.py
tfbox/utils/helpers.py
tfbox/utils/scoring.py
tfbox/utils/tboard.py
tfbox-0.0.0.87.dist-info/LICENSE
tfbox-0.0.0.87.dist-info/METADATA
tfbox-0.0.0.87.dist-info/WHEEL
tfbox-0.0.0.87.dist-info/entry_points.txt
tfbox-0.0.0.87.dist-info/top_level.txt
tfbox-0.0.0.87.dist-info/RECORD
