Metadata-Version: 2.1
Name: tfbox
Version: 0.0.0.87
Summary: tfbox: a collection of models and tools for tensorflow
Home-page: https://github.com/brookisme/tfbox
Author: Brookie Guzder-Williams
Author-email: brook.williams@gmail.com
License: UNKNOWN
Download-URL: https://github.com/brookisme/tfbox/tarball/0.1
Keywords: python,tensorflow,model
Platform: UNKNOWN
Requires-Dist: numpy
Requires-Dist: pandas
Requires-Dist: pyyaml
Requires-Dist: matplotlib
Requires-Dist: imagebox (>=0.0.0.18)
